<?xml version="1.0" encoding="UTF-8" standalone="no"?>
<databaseChangeLog xmlns="http://www.liquibase.org/xml/ns/dbchangelog"
	xmlns:xsi="http://www.w3.org/2001/XMLSchema-instance" xmlns:ext="http://www.liquibase.org/xml/ns/dbchangelog-ext"
	xsi:schemaLocation="http://www.liquibase.org/xml/ns/dbchangelog http://www.liquibase.org/xml/ns/dbchangelog/dbchangelog-2.0.xsd
        http://www.liquibase.org/xml/ns/dbchangelog-ext http://www.liquibase.org/xml/ns/dbchangelog/dbchangelog-ext.xsd">
	<property name="add.schema" value="dbo." dbms="mssql" />
	<property name="add.schema" value=" " dbms="oracle" />
	<property name="call.substr" value="substring" dbms="mssql" />
	<property name="call.substr" value="substr" dbms="oracle" />
	<property name="call.substr" value="substring" dbms="postgresql" />
	<property name="call.auditdb" value="PFFBFSQCAudit.." dbms="mssql" />
	<property name="call.auditdb" value=" " dbms="oracle" />
	<property name="call.concatenate" value="+" dbms="mssql" />
	<property name="call.concatenate" value="||" dbms="oracle" />
	<property name="call.concatenate" value="||" dbms="postgresql" />
	<property name="call.collength" value="LEN" dbms="mssql" />
	<property name="call.collength" value="LENGTH" dbms="oracle" />
	<property name="call.collength" value="LENGTH" dbms="postgresql" />
	<property name="call.date" value="getdate()" dbms="mssql" />
	<property name="call.date" value="sysdate" dbms="oracle" />
	<property name="call.date" value="now()::timestamp" dbms="postgresql" />

	<changeSet id="pre_run_for_pgp" author="murthy.y" runAlways="true"
		dbms="postgresql">
		<sql>
			Set search_path = plfaudit,public,pg_catalog;
		</sql>
	</changeSet>

	<changeSet id="1" author="murthy.y">
		<createTable tableName="adtverifications">
			<column name="AuditId" type="bigint">
				<constraints nullable="false" />
			</column>
			<column name="AuditDate" type="datetime">
				<constraints nullable="false" />
			</column>
			<column name="AuditSeq" type="int">
				<constraints nullable="false" />
			</column>
			<column name="AuditImage" type="char(1)">
				<constraints nullable="false" />
			</column>
			<column name="Id" autoIncrement="true" type="bigint">
				<constraints nullable="false"/>
			</column>
			<column name="VerificationType" type="int" defaultValue="0"
				remarks="Initiate-1, Waive-2, Not Required-3">
				<constraints nullable="false" />
			</column>
			<column name="Module" type="int" defaultValue="0" remarks="Loan-1, Customer-2, Collateral-3"/>
			<column name="KeyReference" type="varchar(20)">
				<constraints nullable="false" />
			</column>
			<column name="ReferenceType" type="varchar(20)">
				<constraints nullable="false" />
			</column>
			<column name="Reference" type="varchar(20)">
				<constraints nullable="false" />
			</column>
			<column name="ReferenceFor" type="varchar(20)" />
			<column name="CustId" type="bigint" />
			<column name="RequestType" type="int" defaultValue="0" remarks="FI-1, TV-2, LV-3, RCU-4"/>
			<column name="Agency" type="bigint" />
			<column name="Reason" type="bigint" />
			<column name="Remarks" type="varchar(500)" />
			<column name="CreatedBy" type="bigint" />
			<column name="CreatedOn" type="datetime" />
			<column name="Status" type="int" defaultValue="0" remarks="Positive-1, Not Completed-2, Waived-3" />
			<column name="AgencyReason" type="bigint" />
			<column name="AgencyRemarks" type="varchar(500)" />
			<column name="VerificationDate" type="datetime" />
			<column name="Decision" type="int" defaultValue="0" remarks="Approve-1, Re-initiate-2, Override-3" />
			<column name="DecisionRemarks" type="varchar(500)" />
			
			<column name="Version" type="int">
				<constraints nullable="false" />
			</column>
			<column name="LastMntBy" type="bigint" />
			<column name="LastMntOn" type="datetime" />
			<column name="RecordStatus" type="varchar(50)" />
			<column name="RoleCode" type="varchar(100)" />
			<column name="NextRoleCode" type="varchar(200)" />
			<column name="TaskId" type="varchar(50)" />
			<column name="NextTaskId" type="varchar(200)" />
			<column name="RecordType" type="varchar(50)" />
			<column name="WorkflowId" type="bigint" />
		</createTable>
	</changeSet>
	<changeSet id="1.1" author="murthy.y">
		<addPrimaryKey tableName="adtverifications"
			columnNames="AuditId, AuditDate, AuditSeq, AuditImage"
			constraintName="pk_adtverifications" />
	</changeSet>
	<changeSet id="2" author="murthy.y">
		<createTable tableName="adtverification_fi">
			<column name="AuditId" type="bigint">
				<constraints nullable="false" />
			</column>
			<column name="AuditDate" type="datetime">
				<constraints nullable="false" />
			</column>
			<column name="AuditSeq" type="int">
				<constraints nullable="false" />
			</column>
			<column name="AuditImage" type="char(1)">
				<constraints nullable="false" />
			</column>
			<column name="VerificationId" type="bigint">
				<constraints nullable="false" />
			</column>
			<column name="AgentCode" type="varchar(20)" />
			<column name="AgentName" type="varchar(50)" />
			<column name="Type" type="int" defaultValue="0"/>
			<column name="Date" type="datetime" />
			<column name="Status" type="int" defaultValue="0"/>
			<column name="Reason" type="bigint" />
			<column name="SummaryRemarks" type="varchar(500)" />			

			<column name="Version" type="int">
				<constraints nullable="false" />
			</column>
			<column name="LastMntBy" type="bigint" />
			<column name="LastMntOn" type="datetime" />
			<column name="RecordStatus" type="varchar(50)" />
			<column name="RoleCode" type="varchar(100)" />
			<column name="NextRoleCode" type="varchar(200)" />
			<column name="TaskId" type="varchar(50)" />
			<column name="NextTaskId" type="varchar(200)" />
			<column name="RecordType" type="varchar(50)" />
			<column name="WorkflowId" type="bigint" />

			<column name="AddressType" type="varchar(8)">
				<constraints nullable="false" />
			</column>
			<column name="Name" type="varchar(200)">
				<constraints nullable="false" />
			</column>
			<column name="HouseNumber" type="varchar(50)" />
			<column name="FlatNumber" type="varchar(50)" />
			<column name="Street" type="varchar(50)" />
			<column name="AddressLine1" type="varchar(50)" />
			<column name="AddressLine2" type="varchar(50)" />
			<column name="AddressLine3" type="varchar(50)" />
			<column name="AddressLine4" type="varchar(50)" />
			<column name="AddressLine5" type="varchar(50)" />
			<column name="Country" type="char(2)" />
			<column name="Province" type="char(2)" />
			<column name="City" type="char(3)" />
			<column name="ContactNumber1" type="varchar(20)" />
			<column name="ContactNumber2" type="varchar(20)" />
			<column name="PoBox" type="varchar(20)" />
			<column name="ZipCode" type="varchar(20)" />
			
			<!-- Observations -->
			<column name="OwnershipStatus" type="int"  defaultValue="0"/>
			<column name="YearsAtPresentAddress" type="int" defaultValue="0"/>
			<column name="PersonMet" type="varchar(50)" />
			<column name="Relationship" type="varchar(8)" />
			<column name="ContactNumber" type="varchar(20)" />
			<column name="NeighbourhoodFeedBack" type="int" defaultValue="0"/>
			<column name="LivingStandard" type="int"  defaultValue="0"/>
			<column name="NegativeCheck" type="smallint" defaultValue="0"/>
			<column name="NoofAttempts" type="int" defaultValue="0"/>
			<column name="ObservationRemarks" type="varchar(500)" />
		</createTable>
	</changeSet>
	<changeSet id="2.1" author="murthy.y">
		<addPrimaryKey tableName="adtverification_fi"
			columnNames="AuditId, AuditDate, AuditSeq, AuditImage"
			constraintName="pk_adtverifications_fi" />
	</changeSet>
	<changeSet id="3" author="manikanta.p">
		<addColumn tableName="adtbmtaddresstypes">
	        <column name="AddrTypeFIRequired" type="smallint"/>
	    </addColumn>
	</changeSet>

	<changeSet id="3.1" author="manikanta.p">
		<sql>
			<![CDATA[
				update adtbmtaddresstypes set AddrTypeFIRequired = 0;
			]]>
		</sql>
	</changeSet>
	<changeSet id="3.2" author="manikanta.p">
		<addDefaultValue columnName="AddrTypeFIRequired" tableName="adtbmtaddresstypes" defaultValueNumeric="0"/>	
	</changeSet>
</databaseChangeLog>