<?xml version="1.0" encoding="UTF-8" standalone="no"?>
<databaseChangeLog xmlns="http://www.liquibase.org/xml/ns/dbchangelog"
	xmlns:xsi="http://www.w3.org/2001/XMLSchema-instance" xmlns:ext="http://www.liquibase.org/xml/ns/dbchangelog-ext"
	xsi:schemaLocation="http://www.liquibase.org/xml/ns/dbchangelog http://www.liquibase.org/xml/ns/dbchangelog/dbchangelog-2.0.xsd
        http://www.liquibase.org/xml/ns/dbchangelog-ext http://www.liquibase.org/xml/ns/dbchangelog/dbchangelog-ext.xsd">

	<property name="add.schema" value="dbo." dbms="mssql" />
	<property name="add.schema" value="" dbms="oracle" />
	<property name="add.schema" value="" dbms="postgresql" />
	<property name="call.substr" value="substring" dbms="mssql" />
	<property name="call.substr" value="substr" dbms="oracle" />
	<property name="call.substr" value="substring" dbms="postgresql" />
	<property name="call.auditdb" value="PLFAVANSEQC.." dbms="mssql" />
	<property name="call.auditdb" value=" " dbms="oracle" />
	<property name="call.concatenate" value="+" dbms="mssql" />
	<property name="call.concatenate" value="||" dbms="oracle" />
	<property name="call.concatenate" value="||" dbms="postgresql" />
	<property name="call.collength" value="LEN" dbms="mssql" />
	<property name="call.collength" value="LENGTH" dbms="oracle" />
	<property name="call.collength" value="LENGTH" dbms="postgresql" />
	<property name="call.date" value="getdate()" dbms="mssql" />
	<property name="call.date" value="sysdate" dbms="oracle" />
	<property name="call.date" value="now()" dbms="postgresql" />

	<changeSet id="pre_run_for_pgp" author="Gopal.p" runAlways="true" dbms="postgresql">
		<sql>
			Set search_path = plf,public,pg_catalog;
		</sql>
	</changeSet>
	
	<changeSet id="ST#730:TK#2762:01" author="Divya.A" >
		<addColumn tableName="ADTRMTFINANCETYPES">
			<column name="writeOffRepayHry" type="varchar(50)"  />
		</addColumn>
	</changeSet>
	
	<changeSet id="ST#730:TK#2762:02" author="Divya.A">
		<addColumn tableName="ADTRMTFINANCETYPES">
			<column name="matureRepayHry" type="varchar(50)" />
		</addColumn>
	</changeSet>
	
	<changeSet id="ST#730:TK#2762:03" author="Divya.A">
		<addColumn tableName="ADTRMTFINANCETYPES">
			<column name="presentmentRepayHry" type="varchar(50)" />
		</addColumn>
	</changeSet>
	
	<changeSet id="ST#730TK#4755.01" author="Vijaayakumar.k">
		<createTable tableName="ADTAUTO_WRITEOFF_LOANTYPES">
			<column name="AUDITID" type="bigint">
				<constraints primaryKey="true" nullable="false" />
			</column>
			<column name="AUDITDATE" type="datetime">
				<constraints primaryKey="true" nullable="false" />
			</column>
			<column name="AUDITSEQ" type="int">
				<constraints primaryKey="true" nullable="false" />
			</column>
			<column name="AUDITIMAGE" type="varchar(20)">
				<constraints primaryKey="true" nullable="false" />
			</column>
			<column name="ID" type="bigint">
				<constraints primaryKey="true" nullable="false" />
			</column>
			<column name="PSLCODE" type="varchar(8)">
				<constraints nullable="false" />
			</column>
			<column name="LoanType" type="varchar(8)">
				<constraints nullable="false" />
			</column>
			<column name="DPDDAYS" type="int">
				<constraints nullable="false" />
			</column>
			<column name="Version" type="int" />
			<column name="LastMntBy" type="bigint" />
			<column name="LastMntOn" type="datetime" />
			<column name="RecordStatus" type="varchar(50)" />
			<column name="RoleCode" type="varchar(100)" />
			<column name="NextRoleCode" type="varchar(200)" />
			<column name="TaskId" type="varchar(50)" />
			<column name="NextTaskId" type="varchar(200)" />
			<column name="RecordType" type="varchar(50)" />
			<column name="WorkflowId" type="bigint" />
		</createTable>
	</changeSet>
	
</databaseChangeLog> 